pyPowerSupplyController/__init__.py
pyPowerSupplyController/emulated_instrument_serial.py
pyPowerSupplyController/exceptions.py
pyPowerSupplyController/manson_instrument.py
pyPowerSupplyController/mi_commands.py
pyPowerSupplyController/models.py
pyPowerSupplyController/serializer.py
pyPowerSupplyController-0.0.8.dist-info/LICENSE.txt
pyPowerSupplyController-0.0.8.dist-info/METADATA
pyPowerSupplyController-0.0.8.dist-info/WHEEL
pyPowerSupplyController-0.0.8.dist-info/top_level.txt
pyPowerSupplyController-0.0.8.dist-info/RECORD
