Metadata-Version: 2.1
Name: pyPowerSupplyController
Version: 0.0.8
Summary: Lab Power Supply Python Library for Serial Programming
Author-email: Joar Gjersund <joar@nofence.no>
Project-URL: Homepage, https://github.com/JoarGjersund/manson_ps_serial_lib
Project-URL: Issues, https://github.com/JoarGjersund/manson_ps_serial_lib/issues
Classifier: Programming Language :: Python :: 3
Classifier: License :: OSI Approved :: GNU General Public License v3 (GPLv3)
Classifier: Operating System :: OS Independent
Requires-Python: >=3.8
License-File: LICENSE.txt
Requires-Dist: pyserial
